expenses/__init__.py
expenses/command_line.py
expenses/expenses.py
expenses/utils.py
expenses/api/__init__.py
expenses/api/exceptions.py
expenses/api/monzo.py
expenses/api/types.py
expenses/api/utilities.py
expenses/templates/example.html
expenses/templates/report.css
expenses/templates/report.html
expenses/templates/report.sass
monzo_expenses-1.0.1.dist-info/LICENSE
monzo_expenses-1.0.1.dist-info/METADATA
monzo_expenses-1.0.1.dist-info/WHEEL
monzo_expenses-1.0.1.dist-info/entry_points.txt
monzo_expenses-1.0.1.dist-info/top_level.txt
monzo_expenses-1.0.1.dist-info/RECORD
