Metadata-Version: 2.1
Name: monzo-expenses
Version: 1.0.1
Summary: Generate expense reports from Monzo
Home-page: https://github.com/samdobson/monzo-expenses
Author: Sam Dobson
Author-email: sjd333@gmail.com
License: UNKNOWN
Platform: UNKNOWN
Classifier: Programming Language :: Python :: 3
Classifier: License :: OSI Approved :: MIT License
Classifier: Operating System :: OS Independent
Requires-Dist: weasyprint
Requires-Dist: jinja2
